yolo_utils.cpython-310-x86_64-linux-gnu.so
yolo_utils-0.1.dist-info/METADATA
yolo_utils-0.1.dist-info/top_level.txt
yolo_utils-0.1.dist-info/RECORD
yolo_utils-0.1.dist-info/WHEEL
